medl/__init__.py
medl/common/__init__.py
medl/common/classes/__init__.py
medl/common/classes/init/__init__.py
medl/common/classes/init/ffmpeg_initializer.py
medl/common/classes/init/folder_initializer.py
medl/common/classes/log_formatter.py
medl/common/classes/logger.py
medl/common/classes/options_manager.py
medl/common/consts/__init__.py
medl/common/consts/paths.py
medl/common/data/__init__.py
medl/common/data/medl_options.py
medl/common/data/playlist_data.py
medl/common/data/song_data.py
medl/common/di/__init__.py
medl/common/di/dependency_injection.py
medl/common/exceptions/__init__.py
medl/common/exceptions/medl_exception.py
medl/common/interfaces/__init__.py
medl/common/interfaces/base_initializer.py
medl/common/interfaces/base_logger.py
medl/common/interfaces/base_options_manager.py
medl/dependency_injection.py
medl/main/__init__.py
medl/main/classes/__init__.py
medl/main/classes/handlers/__init__.py
medl/main/classes/handlers/download_url_finder.py
medl/main/classes/handlers/lyrics_fetcher.py
medl/main/classes/handlers/metadata_embedder.py
medl/main/classes/handlers/metadata_fetcher.py
medl/main/classes/handlers/post_download_handler.py
medl/main/classes/handlers/pre_download_handler.py
medl/main/classes/handlers/track_converter.py
medl/main/classes/handlers/track_downloader.py
medl/main/classes/loggers/__init__.py
medl/main/classes/loggers/download_url_finder_logger.py
medl/main/classes/loggers/lyrics_fetcher_logger.py
medl/main/classes/loggers/metadata_embedder_logger.py
medl/main/classes/loggers/metadata_fetcher_logger.py
medl/main/classes/loggers/track_converter_logger.py
medl/main/classes/loggers/track_downloader_logger.py
medl/main/classes/music_toolbox.py
medl/main/classes/tools/__init__.py
medl/main/classes/tools/downloader.py
medl/main/classes/tools/ffmpeg_converter.py
medl/main/classes/tools/parallelizer.py
medl/main/classes/tools/path_formatter.py
medl/main/data/__init__.py
medl/main/data/download_info.py
medl/main/di/__init__.py
medl-0.1.11.dist-info/LICENSE
medl-0.1.11.dist-info/METADATA
medl-0.1.11.dist-info/WHEEL
medl-0.1.11.dist-info/RECORD
